photo_calendar-0.1.1.data/scripts/photocalendar
photocalendar/__init__.py
photocalendar/photocalendar.py
photocalendar/templates/__init__.py
photocalendar/templates/columba/__init__.py
photocalendar/templates/columba/columba.css
photocalendar/templates/delphinus/__init__.py
photocalendar/templates/delphinus/delphinus.css
photocalendar/templates/html/__init__.py
photocalendar/templates/lupus/__init__.py
photocalendar/templates/lupus/lupus.css
tests/__init__.py
tests/__main__.py
tests/test_1.py
tests/test_html.py
photo_calendar-0.1.1.dist-info/LICENSE
photo_calendar-0.1.1.dist-info/METADATA
photo_calendar-0.1.1.dist-info/WHEEL
photo_calendar-0.1.1.dist-info/top_level.txt
photo_calendar-0.1.1.dist-info/RECORD
