Metadata-Version: 2.1
Name: photo-calendar
Version: 0.1.1
Summary: Creates custom weekly/monthly/... photo calendars
Home-page: https://github.com/stranskyjan/photo-calendar
Author: Jan Stránský
Author-email: honzik.stransky@gmail.com
License: LGPL
Keywords: photocalendar photo calendar
Platform: UNKNOWN
Classifier: Development Status :: 4 - Beta
Classifier: License :: OSI Approved :: GNU Lesser General Public License v3 (LGPLv3)
Classifier: Programming Language :: Python
Classifier: Programming Language :: Python :: 2
Classifier: Programming Language :: Python :: 3
Classifier: Programming Language :: Unix Shell
Classifier: Operating System :: OS Independent
